modularitydensity/.DS_Store
modularitydensity/__init__.py
modularitydensity/constrained_fine_tuned_modularity.py
modularitydensity/constrained_fine_tuned_modularity_density.py
modularitydensity/fine_tuned_modularity.py
modularitydensity/fine_tuned_modularity_density.py
modularitydensity/metrics.py
modularitydensity-0.0.6.dist-info/LICENSE.txt
modularitydensity-0.0.6.dist-info/METADATA
modularitydensity-0.0.6.dist-info/WHEEL
modularitydensity-0.0.6.dist-info/top_level.txt
modularitydensity-0.0.6.dist-info/RECORD
