Metadata-Version: 2.1
Name: modularitydensity
Version: 0.0.6
Summary: Run modularity density-based clustering
Home-page: https://github.com/ckmanalytix/modularity-density
License: MIT License (MIT License)
Platform: UNKNOWN
Classifier: Programming Language :: Python
Requires-Python: >= 3.5
Requires-Dist: numpy (>=1.15.1)
Requires-Dist: scipy (>=1.1.0)
Requires-Dist: networkx (>=2.2)
Provides-Extra: testing
Requires-Dist: pytest ; extra == 'testing'
Requires-Dist: pytest-cov ; extra == 'testing'
